build_uvm_src.py
dv_flow/libhdlsim/__ext__.py
dv_flow/libhdlsim/__init__.py
dv_flow/libhdlsim/flow.dv
dv_flow/libhdlsim/ivl_flow.dv
dv_flow/libhdlsim/ivl_sim_image.py
dv_flow/libhdlsim/ivl_sim_run.py
dv_flow/libhdlsim/log_parser.py
dv_flow/libhdlsim/mti_flow.dv
dv_flow/libhdlsim/mti_log_parser.py
dv_flow/libhdlsim/mti_sim_image.py
dv_flow/libhdlsim/mti_sim_lib.py
dv_flow/libhdlsim/mti_sim_run.py
dv_flow/libhdlsim/sim_args.py
dv_flow/libhdlsim/util.py
dv_flow/libhdlsim/vcs_flow.dv
dv_flow/libhdlsim/vcs_log_parser.py
dv_flow/libhdlsim/vcs_sim_image.py
dv_flow/libhdlsim/vcs_sim_lib.py
dv_flow/libhdlsim/vcs_sim_lib_uvm.py
dv_flow/libhdlsim/vcs_sim_run.py
dv_flow/libhdlsim/vl_sim_data.py
dv_flow/libhdlsim/vl_sim_image_builder.py
dv_flow/libhdlsim/vl_sim_lib_builder.py
dv_flow/libhdlsim/vl_sim_runner.py
dv_flow/libhdlsim/vlt_flow.dv
dv_flow/libhdlsim/vlt_log_parser.py
dv_flow/libhdlsim/vlt_sim_image.py
dv_flow/libhdlsim/vlt_sim_lib_uvm.py
dv_flow/libhdlsim/vlt_sim_run.py
dv_flow/libhdlsim/xcm_flow.dv
dv_flow/libhdlsim/xcm_sim_image.py
dv_flow/libhdlsim/xcm_sim_run.py
dv_flow/libhdlsim/xsm_flow.dv
dv_flow/libhdlsim/xsm_log_parser.py
dv_flow/libhdlsim/xsm_sim_image.py
dv_flow/libhdlsim/xsm_sim_lib_uvm.py
dv_flow/libhdlsim/xsm_sim_run.py
dv_flow/libhdlsim/pytest/__init__.py
dv_flow/libhdlsim/share/uvm_src.tar.bz2
dv_flow_libhdlsim-0.0.521368995911.dist-info/licenses/LICENSE
dv_flow_libhdlsim-0.0.521368995911.dist-info/METADATA
dv_flow_libhdlsim-0.0.521368995911.dist-info/WHEEL
dv_flow_libhdlsim-0.0.521368995911.dist-info/entry_points.txt
dv_flow_libhdlsim-0.0.521368995911.dist-info/top_level.txt
dv_flow_libhdlsim-0.0.521368995911.dist-info/RECORD
