Metadata-Version: 2.4
Name: dv-flow-libhdlsim
Version: 0.0.521368995911
Summary: Provides dv-flow tasks for performing common tasks related to HDL simulation
Author-email: Matthew Ballance <matt.ballance@gmail.com>
License:                                  Apache License
License-File: LICENSE
Requires-Dist: dv-flow-mgr
Requires-Dist: toposort
Dynamic: license-file
